pyisstelemetry/__init__.py
pyisstelemetry/lightstreamer.py
pyisstelemetry/tm.list
py_iss_telemetry-1.2.dist-info/LICENSE
py_iss_telemetry-1.2.dist-info/METADATA
py_iss_telemetry-1.2.dist-info/WHEEL
py_iss_telemetry-1.2.dist-info/top_level.txt
py_iss_telemetry-1.2.dist-info/RECORD
