Metadata-Version: 2.1
Name: py-iss-telemetry
Version: 1.2
Summary: Stream live International Space Station Telemetry.
Home-page: https://github.com/BApplB/py-iss-telemetry
Author: Ben Appleby
Author-email: ben.appleby@sky.com
License: UNKNOWN
Platform: UNKNOWN
Classifier: Programming Language :: Python :: 3
Classifier: License :: OSI Approved :: Apache Software License
Classifier: Operating System :: OS Independent
Requires-Python: >=3.5
